ambition_pharmacy/__init__.py
ambition_pharmacy/apps.py
ambition_pharmacy/urls.py
ambition_pharmacy/tests/__init__.py
ambition_pharmacy/tests/tests_pharmacy.py
ambition_pharmacy-0.1.6.dist-info/AUTHORS
ambition_pharmacy-0.1.6.dist-info/LICENSE
ambition_pharmacy-0.1.6.dist-info/METADATA
ambition_pharmacy-0.1.6.dist-info/WHEEL
ambition_pharmacy-0.1.6.dist-info/top_level.txt
ambition_pharmacy-0.1.6.dist-info/RECORD
